README.md
setup.py
Kickdomain.egg-info/PKG-INFO
Kickdomain.egg-info/SOURCES.txt
Kickdomain.egg-info/dependency_links.txt
Kickdomain.egg-info/requires.txt
Kickdomain.egg-info/top_level.txt
kickdomain/__init__.py
kickdomain/config.py
kickdomain/kickdomain.py
kickdomain/portscanner.py
provider/__init__.py
provider/config.py
provider/portscanner.py
provider/providers.py