Metadata-Version: 2.1
Name: Kickdomain
Version: 1.4
Summary: Subdomain takeover tool
Home-page: https://github.com/abuvanth/kickdomain
Author: Syed Abuthahir
Author-email: developerabu@gmail.com
License: UNKNOWN
Platform: UNKNOWN
Classifier: Programming Language :: Python :: 3
Classifier: License :: OSI Approved :: MIT License
Classifier: Operating System :: OS Independent
